setup.py
zone_file/__init__.py
zone_file/configs.py
zone_file/exceptions.py
zone_file/make_zone_file.py
zone_file/parse_zone_file.py
zone_file/record_processors.py
zone_file.egg-info/PKG-INFO
zone_file.egg-info/SOURCES.txt
zone_file.egg-info/dependency_links.txt
zone_file.egg-info/not-zip-safe
zone_file.egg-info/top_level.txt