Metadata-Version: 1.1
Name: zone-file
Version: 0.1.4
Summary: Library for creating and parsing DNS zone files
Home-page: https://github.com/blockstack/dns-zone-file-py
Author: Blockstack Developers
Author-email: hello@onename.com
License: MIT
Keywords: dns zone file zonefile parse create
Platform: UNKNOWN
Classifier: Intended Audience :: Developers
Classifier: License :: OSI Approved :: MIT License
Classifier: Operating System :: OS Independent
Classifier: Programming Language :: Python
Classifier: Topic :: Internet
Classifier: Topic :: Software Development :: Libraries :: Python Modules
